ApacheAirflowIncubatingDocumentation/README.md
ApacheAirflowIncubatingDocumentation/__init__.py
ApacheAirflowIncubatingDocumentation/__main__.py
ApacheAirflowIncubatingDocumentation/file.epub
ApacheAirflowIncubatingDocumentation/index.html
ApacheAirflowIncubatingDocumentation/css/__init__.py
ApacheAirflowIncubatingDocumentation/css/annotations.css
ApacheAirflowIncubatingDocumentation/css/main.css
ApacheAirflowIncubatingDocumentation/css/normalize.css
ApacheAirflowIncubatingDocumentation/css/popup.css
ApacheAirflowIncubatingDocumentation/font/__init__.py
ApacheAirflowIncubatingDocumentation/font/fontello.eot
ApacheAirflowIncubatingDocumentation/font/fontello.svg
ApacheAirflowIncubatingDocumentation/font/fontello.ttf
ApacheAirflowIncubatingDocumentation/font/fontello.woff
ApacheAirflowIncubatingDocumentation/img/__init__.py
ApacheAirflowIncubatingDocumentation/img/annotator-glyph-sprite.png
ApacheAirflowIncubatingDocumentation/img/annotator-icon-sprite.png
ApacheAirflowIncubatingDocumentation/img/apple-touch-icon.png
ApacheAirflowIncubatingDocumentation/img/cancelfullscreen.png
ApacheAirflowIncubatingDocumentation/img/close.png
ApacheAirflowIncubatingDocumentation/img/fullscreen.png
ApacheAirflowIncubatingDocumentation/img/loader.gif
ApacheAirflowIncubatingDocumentation/img/menu-icon.png
ApacheAirflowIncubatingDocumentation/img/save.png
ApacheAirflowIncubatingDocumentation/img/saved.png
ApacheAirflowIncubatingDocumentation/img/settings-s.png
ApacheAirflowIncubatingDocumentation/img/settings.png
ApacheAirflowIncubatingDocumentation/img/star.png
ApacheAirflowIncubatingDocumentation/js/__init__.py
ApacheAirflowIncubatingDocumentation/js/epub.js
ApacheAirflowIncubatingDocumentation/js/epub.min.js
ApacheAirflowIncubatingDocumentation/js/epub.min.map
ApacheAirflowIncubatingDocumentation/js/hooks.min.js
ApacheAirflowIncubatingDocumentation/js/hooks.min.map
ApacheAirflowIncubatingDocumentation/js/reader.js
ApacheAirflowIncubatingDocumentation/js/reader.js.map
apache_airflow_incubating_documentation-2024.3.3.0.dist-info/METADATA
apache_airflow_incubating_documentation-2024.3.3.0.dist-info/WHEEL
apache_airflow_incubating_documentation-2024.3.3.0.dist-info/entry_points.txt
apache_airflow_incubating_documentation-2024.3.3.0.dist-info/top_level.txt
apache_airflow_incubating_documentation-2024.3.3.0.dist-info/RECORD
